trading212/__init__.py
trading212/models.py
trading212/trading212.py
python_trading212_alinalihassan-2.0.5.dist-info/LICENSE.md
python_trading212_alinalihassan-2.0.5.dist-info/METADATA
python_trading212_alinalihassan-2.0.5.dist-info/WHEEL
python_trading212_alinalihassan-2.0.5.dist-info/RECORD
